{
    "annotations": {
        "list": [
            {
                "builtIn": 1,
                "datasource": "-- Grafana --",
                "enable": true,
                "hide": true,
                "iconColor": "rgba(0, 211, 255, 1)",
                "name": "Annotations & Alerts",
                "target": {
                    "limit": 100,
                    "matchAny": false,
                    "tags": [],
                    "type": "dashboard"
                },
                "type": "dashboard"
            }
        ]
    },
    "description": "\u041e\u0442\u0432\u0435\u0442\u0441\u0442\u0432\u0435\u043d\u043d\u044b\u0439: \u0413\u043e\u043b\u0443\u0431\u0435\u0432 \u0410.\u0424. (\u0420\u0430\u0437\u0440\u0430\u0431\u043e\u0442\u043a\u0430)",
    "editable": true,
    "fiscalYearStartMonth": 0,
    "gnetId": null,
    "graphTooltip": 1,
    "id": 1724,
    "iteration": 1647420968136,
    "links": [
        {
            "asDropdown": true,
            "icon": "external link",
            "includeVars": false,
            "keepTime": false,
            "tags": [
                "hlha"
            ],
            "targetBlank": false,
            "title": "HLHA",
            "tooltip": "",
            "type": "dashboards",
            "url": ""
        }
    ],
    "liveNow": false,
    "panels": [
        {
            "datasource": "Tagged",
            "description": "\u0421\u043e\u0441\u0442\u043e\u044f\u043d\u0438\u0435 TCP \u0441\u043e\u0435\u0434\u0438\u043d\u0435\u043d\u0438\u0439",
            "fieldConfig": {
                "defaults": {
                    "color": {
                        "mode": "palette-classic"
                    },
                    "custom": {
                        "axisLabel": "",
                        "axisPlacement": "auto",
                        "barAlignment": 0,
                        "drawStyle": "line",
                        "fillOpacity": 50,
                        "gradientMode": "opacity",
                        "hideFrom": {
                            "legend": false,
                            "tooltip": false,
                            "viz": false
                        },
                        "lineInterpolation": "linear",
                        "lineStyle": {
                            "fill": "solid"
                        },
                        "lineWidth": 1,
                        "pointSize": 5,
                        "scaleDistribution": {
                            "type": "linear"
                        },
                        "showPoints": "never",
                        "spanNulls": true,
                        "stacking": {
                            "group": "A",
                            "mode": "normal"
                        },
                        "thresholdsStyle": {
                            "mode": "off"
                        }
                    },
                    "decimals": 0,
                    "links": [],
                    "mappings": [],
                    "min": 0,
                    "thresholds": {
                        "mode": "absolute",
                        "steps": [
                            {
                                "color": "green",
                                "value": null
                            }
                        ]
                    },
                    "unit": "short"
                },
                "overrides": []
            },
            "gridPos": {
                "h": 7,
                "w": 12,
                "x": 0,
                "y": 0
            },
            "id": 10,
            "options": {
                "legend": {
                    "calcs": [
                        "mean",
                        "max",
                        "min"
                    ],
                    "displayMode": "table",
                    "placement": "right"
                },
                "tooltip": {
                    "mode": "single"
                }
            },
            "pluginVersion": "8.2.3",
            "targets": [
                {
                    "refId": "A",
                    "target": "aliasByNode(aliasByTags(sortByMaxima(seriesByTag('name=~system.netstat.*', 'host=~${host:regex}')), 'name'), 2)"
                }
            ],
            "timeFrom": null,
            "timeShift": null,
            "title": "\u0421\u0415\u0422\u042c / TCP",
            "type": "timeseries"
        },
        {
            "aliasColors": {},
            "bars": false,
            "dashLength": 10,
            "dashes": false,
            "datasource": "Tagged",
            "decimals": 0,
            "description": "struct \u2014 \u0441\u043a\u043e\u043b\u044c\u043a\u043e \u0441\u0442\u0440\u0443\u043a\u0442\u0443\u0440 \u0432\u044b\u0434\u0435\u043b\u0435\u043d\u043e \u0432 \u043c\u0435\u043c\u043a\u0435\u0448\u0435 \u0434\u043b\u044f \u043f\u0440\u0438\u0435\u043c\u0430 \u043a\u043e\u043d\u043d\u0435\u043a\u0442\u043e\u0432. \u0434\u043e\u043b\u0436\u043d\u0430 \u0431\u044b\u0442\u044c \u043d\u0435\u043c\u043d\u043e\u0433\u043e \u0431\u043e\u043b\u044c\u0448\u0435 \u0447\u0435\u043c \u0442\u0435\u043a\u0443\u0447\u043a\u0430.\n\nconnection \u2014 \u0442\u0435\u043a\u0443\u0449\u0438\u0435 \u043a\u043e\u043d\u043d\u0435\u043a\u0442\u044b",
            "fill": 1,
            "fillGradient": 0,
            "gridPos": {
                "h": 7,
                "w": 12,
                "x": 12,
                "y": 0
            },
            "hiddenSeries": false,
            "id": 13,
            "legend": {
                "alignAsTable": true,
                "avg": true,
                "current": false,
                "max": true,
                "min": true,
                "rightSide": true,
                "show": true,
                "sideWidth": 350,
                "total": false,
                "values": true
            },
            "lines": true,
            "linewidth": 1,
            "nullPointMode": "null",
            "options": {
                "alertThreshold": true
            },
            "percentage": false,
            "pluginVersion": "8.2.3",
            "pointradius": 2,
            "points": false,
            "renderer": "flot",
            "seriesOverrides": [
                {
                    "$$hashKey": "object:182",
                    "alias": "struct",
                    "color": "#C4162A",
                    "fill": 0,
                    "fillGradient": 0
                },
                {
                    "$$hashKey": "object:368",
                    "alias": "connection",
                    "color": "#37872D",
                    "fillGradient": 5
                }
            ],
            "spaceLength": 10,
            "stack": false,
            "steppedLine": false,
            "targets": [
                {
                    "hide": false,
                    "refCount": 0,
                    "refId": "C",
                    "target": "alias(seriesByTag('host=~${host:regex}', 'name=memcached.connection_structures', 'servertype=memcached'), 'struct')"
                },
                {
                    "refCount": 0,
                    "refId": "A",
                    "target": "alias(seriesByTag('host=~${host:regex}', 'name=memcached.curr_connections', 'servertype=memcached'), 'connection')"
                }
            ],
            "thresholds": [],
            "timeFrom": null,
            "timeRegions": [],
            "timeShift": null,
            "title": "\u0421\u043e\u0435\u0434\u0438\u043d\u0435\u043d\u0438\u044f",
            "tooltip": {
                "shared": true,
                "sort": 0,
                "value_type": "individual"
            },
            "type": "graph",
            "xaxis": {
                "buckets": null,
                "mode": "time",
                "name": null,
                "show": true,
                "values": []
            },
            "yaxes": [
                {
                    "$$hashKey": "object:360",
                    "decimals": 0,
                    "format": "short",
                    "label": null,
                    "logBase": 1,
                    "max": null,
                    "min": "0",
                    "show": true
                },
                {
                    "$$hashKey": "object:361",
                    "format": "short",
                    "label": null,
                    "logBase": 1,
                    "max": null,
                    "min": null,
                    "show": false
                }
            ],
            "yaxis": {
                "align": false,
                "alignLevel": null
            }
        },
        {
            "aliasColors": {},
            "bars": false,
            "dashLength": 10,
            "dashes": false,
            "datasource": "Tagged",
            "description": "\u0421\u043a\u043e\u0440\u043e\u0441\u0442\u044c \u0442\u0435\u043a\u0443\u0449\u0438\u0445 \u043f\u043e\u0434\u043a\u043b\u044e\u0447\u0435\u043d\u0438\u0439",
            "fill": 1,
            "fillGradient": 0,
            "gridPos": {
                "h": 6,
                "w": 12,
                "x": 0,
                "y": 7
            },
            "hiddenSeries": false,
            "id": 7,
            "legend": {
                "avg": false,
                "current": false,
                "max": false,
                "min": false,
                "show": false,
                "total": false,
                "values": false
            },
            "lines": true,
            "linewidth": 1,
            "nullPointMode": "null",
            "options": {
                "alertThreshold": true
            },
            "percentage": false,
            "pluginVersion": "8.2.3",
            "pointradius": 2,
            "points": false,
            "renderer": "flot",
            "seriesOverrides": [],
            "spaceLength": 10,
            "stack": false,
            "steppedLine": false,
            "targets": [
                {
                    "refId": "A",
                    "target": "alias(nonNegativeDerivative(seriesByTag('host=~${host:regex}', 'name=memcached.total_connections', 'servertype=memcached')), 'connections')"
                }
            ],
            "thresholds": [],
            "timeFrom": null,
            "timeRegions": [],
            "timeShift": null,
            "title": "Connection(s) RPS",
            "tooltip": {
                "shared": true,
                "sort": 0,
                "value_type": "individual"
            },
            "type": "graph",
            "xaxis": {
                "buckets": null,
                "mode": "time",
                "name": null,
                "show": true,
                "values": []
            },
            "yaxes": [
                {
                    "$$hashKey": "object:360",
                    "decimals": null,
                    "format": "reqps",
                    "label": null,
                    "logBase": 1,
                    "max": null,
                    "min": null,
                    "show": true
                },
                {
                    "$$hashKey": "object:361",
                    "format": "short",
                    "label": null,
                    "logBase": 1,
                    "max": null,
                    "min": null,
                    "show": true
                }
            ],
            "yaxis": {
                "align": false,
                "alignLevel": null
            }
        },
        {
            "datasource": "Tagged",
            "description": "\u041a\u043e\u043b-\u0432\u043e \u043a\u043b\u044e\u0447\u0435\u0439 \u0432 \u043c\u0435\u043c\u043a\u0435\u0448\u0435",
            "fieldConfig": {
                "defaults": {
                    "color": {
                        "mode": "palette-classic"
                    },
                    "custom": {
                        "axisLabel": "",
                        "axisPlacement": "auto",
                        "barAlignment": 0,
                        "drawStyle": "line",
                        "fillOpacity": 10,
                        "gradientMode": "none",
                        "hideFrom": {
                            "legend": false,
                            "tooltip": false,
                            "viz": false
                        },
                        "lineInterpolation": "linear",
                        "lineWidth": 1,
                        "pointSize": 5,
                        "scaleDistribution": {
                            "type": "linear"
                        },
                        "showPoints": "never",
                        "spanNulls": true,
                        "stacking": {
                            "group": "A",
                            "mode": "none"
                        },
                        "thresholdsStyle": {
                            "mode": "off"
                        }
                    },
                    "decimals": 1,
                    "mappings": [],
                    "min": 0,
                    "thresholds": {
                        "mode": "absolute",
                        "steps": [
                            {
                                "color": "green",
                                "value": null
                            },
                            {
                                "color": "red",
                                "value": 80
                            }
                        ]
                    },
                    "unit": "short"
                },
                "overrides": []
            },
            "gridPos": {
                "h": 6,
                "w": 12,
                "x": 12,
                "y": 7
            },
            "id": 8,
            "options": {
                "legend": {
                    "calcs": [],
                    "displayMode": "hidden",
                    "placement": "bottom"
                },
                "tooltip": {
                    "mode": "single"
                }
            },
            "pluginVersion": "8.2.3",
            "targets": [
                {
                    "refId": "A",
                    "target": "alias(seriesByTag('host=~${host:regex}', 'name=memcached.curr_items', 'servertype=memcached'), 'items')"
                }
            ],
            "timeFrom": null,
            "timeShift": null,
            "title": "\u041a\u043b\u044e\u0447\u0438",
            "type": "timeseries"
        },
        {
            "aliasColors": {},
            "bars": false,
            "dashLength": 10,
            "dashes": false,
            "datasource": "Tagged",
            "decimals": 0,
            "description": "\u041a\u043e\u043c\u0430\u043d\u0434\u044b \u0447\u0442\u0435\u043d\u0438\u044f/\u0437\u0430\u043f\u0438\u0441\u0438",
            "fill": 1,
            "fillGradient": 0,
            "gridPos": {
                "h": 6,
                "w": 12,
                "x": 0,
                "y": 13
            },
            "hiddenSeries": false,
            "id": 15,
            "legend": {
                "alignAsTable": true,
                "avg": true,
                "current": false,
                "max": true,
                "min": false,
                "rightSide": true,
                "show": true,
                "sideWidth": 250,
                "total": false,
                "values": true
            },
            "lines": true,
            "linewidth": 1,
            "nullPointMode": "null",
            "options": {
                "alertThreshold": true
            },
            "percentage": false,
            "pluginVersion": "8.2.3",
            "pointradius": 2,
            "points": false,
            "renderer": "flot",
            "seriesOverrides": [
                {
                    "$$hashKey": "object:627",
                    "alias": "set",
                    "color": "#C4162A",
                    "transform": "negative-Y"
                },
                {
                    "$$hashKey": "object:639",
                    "alias": "get",
                    "color": "#37872D"
                }
            ],
            "spaceLength": 10,
            "stack": false,
            "steppedLine": false,
            "targets": [
                {
                    "refCount": 0,
                    "refId": "A",
                    "target": "alias(perSecond(seriesByTag('host=~${host:regex}', 'name=memcached.cmd_get', 'servertype=memcached')), 'get')"
                },
                {
                    "hide": false,
                    "refCount": 0,
                    "refId": "B",
                    "target": "alias(perSecond(seriesByTag('host=~${host:regex}', 'name=memcached.cmd_set', 'servertype=memcached')), 'set')"
                }
            ],
            "thresholds": [],
            "timeFrom": null,
            "timeRegions": [],
            "timeShift": null,
            "title": "GET/SET",
            "tooltip": {
                "shared": true,
                "sort": 0,
                "value_type": "individual"
            },
            "type": "graph",
            "xaxis": {
                "buckets": null,
                "mode": "time",
                "name": null,
                "show": true,
                "values": []
            },
            "yaxes": [
                {
                    "$$hashKey": "object:360",
                    "decimals": 0,
                    "format": "short",
                    "label": null,
                    "logBase": 1,
                    "max": null,
                    "min": null,
                    "show": true
                },
                {
                    "$$hashKey": "object:361",
                    "format": "short",
                    "label": null,
                    "logBase": 1,
                    "max": null,
                    "min": null,
                    "show": false
                }
            ],
            "yaxis": {
                "align": false,
                "alignLevel": null
            }
        },
        {
            "aliasColors": {},
            "bars": false,
            "dashLength": 10,
            "dashes": false,
            "datasource": "Tagged",
            "decimals": 0,
            "description": "\u041f\u043e\u043f\u0430\u0434\u0430\u043d\u0438\u044f/\u043f\u0440\u043e\u043c\u0430\u0445\u0438 \u0432 \u043a\u0435\u0448",
            "fill": 1,
            "fillGradient": 0,
            "gridPos": {
                "h": 6,
                "w": 12,
                "x": 12,
                "y": 13
            },
            "hiddenSeries": false,
            "id": 17,
            "legend": {
                "alignAsTable": true,
                "avg": true,
                "current": false,
                "max": true,
                "min": false,
                "rightSide": true,
                "show": true,
                "sideWidth": 250,
                "total": false,
                "values": true
            },
            "lines": true,
            "linewidth": 1,
            "nullPointMode": "null",
            "options": {
                "alertThreshold": true
            },
            "percentage": false,
            "pluginVersion": "8.2.3",
            "pointradius": 2,
            "points": false,
            "renderer": "flot",
            "seriesOverrides": [
                {
                    "$$hashKey": "object:627",
                    "alias": "miss",
                    "color": "#C4162A",
                    "transform": "negative-Y"
                },
                {
                    "$$hashKey": "object:639",
                    "alias": "hit",
                    "color": "#37872D"
                }
            ],
            "spaceLength": 10,
            "stack": false,
            "steppedLine": false,
            "targets": [
                {
                    "refCount": 0,
                    "refId": "A",
                    "target": "alias(perSecond(seriesByTag('host=~${host:regex}', 'name=memcached.get_hits', 'servertype=memcached')), 'hit')",
                    "textEditor": false
                },
                {
                    "hide": false,
                    "refCount": 0,
                    "refId": "B",
                    "target": "alias(perSecond(seriesByTag('host=~${host:regex}', 'name=memcached.get_misses', 'servertype=memcached')), 'miss')"
                }
            ],
            "thresholds": [],
            "timeFrom": null,
            "timeRegions": [],
            "timeShift": null,
            "title": "HIT/MISS",
            "tooltip": {
                "shared": true,
                "sort": 0,
                "value_type": "individual"
            },
            "type": "graph",
            "xaxis": {
                "buckets": null,
                "mode": "time",
                "name": null,
                "show": true,
                "values": []
            },
            "yaxes": [
                {
                    "$$hashKey": "object:360",
                    "decimals": 0,
                    "format": "short",
                    "label": null,
                    "logBase": 1,
                    "max": null,
                    "min": null,
                    "show": true
                },
                {
                    "$$hashKey": "object:361",
                    "format": "short",
                    "label": null,
                    "logBase": 1,
                    "max": null,
                    "min": null,
                    "show": false
                }
            ],
            "yaxis": {
                "align": false,
                "alignLevel": null
            }
        },
        {
            "aliasColors": {},
            "bars": false,
            "dashLength": 10,
            "dashes": false,
            "datasource": "Tagged",
            "description": "\u0420\u0430\u0437\u043c\u0435\u0440 \u043a\u0435\u0448\u0430",
            "fill": 1,
            "fillGradient": 0,
            "gridPos": {
                "h": 6,
                "w": 12,
                "x": 0,
                "y": 19
            },
            "hiddenSeries": false,
            "id": 19,
            "legend": {
                "avg": false,
                "current": false,
                "max": false,
                "min": false,
                "show": false,
                "total": false,
                "values": false
            },
            "lines": true,
            "linewidth": 1,
            "nullPointMode": "null",
            "options": {
                "alertThreshold": true
            },
            "percentage": false,
            "pluginVersion": "8.2.3",
            "pointradius": 2,
            "points": false,
            "renderer": "flot",
            "seriesOverrides": [
                {
                    "$$hashKey": "object:890",
                    "alias": "bytes",
                    "color": "#37872D"
                }
            ],
            "spaceLength": 10,
            "stack": false,
            "steppedLine": false,
            "targets": [
                {
                    "refId": "A",
                    "target": "alias(seriesByTag('host=~${host:regex}', 'name=memcached.bytes', 'servertype=memcached'), 'bytes')"
                }
            ],
            "thresholds": [],
            "timeFrom": null,
            "timeRegions": [],
            "timeShift": null,
            "title": "BYTES",
            "tooltip": {
                "shared": true,
                "sort": 0,
                "value_type": "individual"
            },
            "type": "graph",
            "xaxis": {
                "buckets": null,
                "mode": "time",
                "name": null,
                "show": true,
                "values": []
            },
            "yaxes": [
                {
                    "$$hashKey": "object:360",
                    "decimals": 1,
                    "format": "bytes",
                    "label": null,
                    "logBase": 1,
                    "max": null,
                    "min": "0",
                    "show": true
                },
                {
                    "$$hashKey": "object:361",
                    "format": "short",
                    "label": null,
                    "logBase": 1,
                    "max": null,
                    "min": null,
                    "show": false
                }
            ],
            "yaxis": {
                "align": false,
                "alignLevel": null
            }
        },
        {
            "aliasColors": {},
            "bars": false,
            "dashLength": 10,
            "dashes": false,
            "datasource": "Tagged",
            "decimals": null,
            "description": "\u0422\u0440\u0430\u0444\u0438\u043a \u0447\u0442\u0435\u043d\u0438\u044f/\u0437\u0430\u043f\u0438\u0441\u0438",
            "fill": 1,
            "fillGradient": 0,
            "gridPos": {
                "h": 6,
                "w": 12,
                "x": 12,
                "y": 19
            },
            "hiddenSeries": false,
            "id": 21,
            "legend": {
                "alignAsTable": true,
                "avg": true,
                "current": false,
                "max": true,
                "min": false,
                "rightSide": true,
                "show": true,
                "sideWidth": 250,
                "total": false,
                "values": true
            },
            "lines": true,
            "linewidth": 1,
            "nullPointMode": "null",
            "options": {
                "alertThreshold": true
            },
            "percentage": false,
            "pluginVersion": "8.2.3",
            "pointradius": 2,
            "points": false,
            "renderer": "flot",
            "seriesOverrides": [
                {
                    "$$hashKey": "object:366",
                    "alias": "written",
                    "color": "#C4162A",
                    "transform": "negative-Y"
                },
                {
                    "$$hashKey": "object:626",
                    "alias": "read",
                    "color": "#37872D"
                }
            ],
            "spaceLength": 10,
            "stack": false,
            "steppedLine": false,
            "targets": [
                {
                    "refCount": 0,
                    "refId": "A",
                    "target": "alias(perSecond(seriesByTag('host=~${host:regex}', 'name=memcached.bytes_read', 'servertype=memcached')), 'read')"
                },
                {
                    "hide": false,
                    "refCount": 0,
                    "refId": "B",
                    "target": "alias(perSecond(seriesByTag('host=~${host:regex}', 'name=memcached.bytes_written', 'servertype=memcached')), 'written')"
                }
            ],
            "thresholds": [],
            "timeFrom": null,
            "timeRegions": [],
            "timeShift": null,
            "title": "READ/WRITTEN",
            "tooltip": {
                "shared": true,
                "sort": 0,
                "value_type": "individual"
            },
            "type": "graph",
            "xaxis": {
                "buckets": null,
                "mode": "time",
                "name": null,
                "show": true,
                "values": []
            },
            "yaxes": [
                {
                    "$$hashKey": "object:360",
                    "decimals": 1,
                    "format": "bytes",
                    "label": null,
                    "logBase": 1,
                    "max": null,
                    "min": null,
                    "show": true
                },
                {
                    "$$hashKey": "object:361",
                    "format": "short",
                    "label": null,
                    "logBase": 1,
                    "max": null,
                    "min": null,
                    "show": false
                }
            ],
            "yaxis": {
                "align": false,
                "alignLevel": null
            }
        },
        {
            "aliasColors": {},
            "bars": false,
            "dashLength": 10,
            "dashes": false,
            "datasource": "Tagged",
            "description": "\u0412\u044b\u0441\u0435\u043b\u0435\u043d\u043d\u044b\u0435 \u043a\u043b\u044e\u0447\u0438 \u043a\u043e\u0433\u0434\u0430 \u043d\u0435 \u0445\u0432\u0430\u0442\u0430\u0435\u0442 \u043c\u0435\u0441\u0442\u0430. \u0414\u043e\u043b\u0436\u043d\u043e \u0431\u044b\u0442\u044c \u0432 \u043d\u043e\u043b\u044c. \u0415\u0441\u043b\u0438 \u043d\u0435 \u043d\u043e\u043b\u044c - \u0434\u043e\u0431\u0430\u0432\u043b\u044f\u0442\u044c \u043f\u0430\u043c\u044f\u0442\u0438 memcached",
            "fill": 1,
            "fillGradient": 0,
            "gridPos": {
                "h": 6,
                "w": 12,
                "x": 0,
                "y": 25
            },
            "hiddenSeries": false,
            "id": 23,
            "legend": {
                "avg": false,
                "current": false,
                "max": false,
                "min": false,
                "show": false,
                "total": false,
                "values": false
            },
            "lines": true,
            "linewidth": 1,
            "nullPointMode": "null",
            "options": {
                "alertThreshold": true
            },
            "percentage": false,
            "pluginVersion": "8.2.3",
            "pointradius": 2,
            "points": false,
            "renderer": "flot",
            "seriesOverrides": [],
            "spaceLength": 10,
            "stack": false,
            "steppedLine": false,
            "targets": [
                {
                    "refId": "A",
                    "target": "alias(seriesByTag('host=~${host:regex}', 'name=memcached.evictions', 'servertype=memcached'), 'items')"
                }
            ],
            "thresholds": [],
            "timeFrom": null,
            "timeRegions": [],
            "timeShift": null,
            "title": "EVICTIONS",
            "tooltip": {
                "shared": true,
                "sort": 0,
                "value_type": "individual"
            },
            "type": "graph",
            "xaxis": {
                "buckets": null,
                "mode": "time",
                "name": null,
                "show": true,
                "values": []
            },
            "yaxes": [
                {
                    "$$hashKey": "object:360",
                    "decimals": 0,
                    "format": "none",
                    "label": null,
                    "logBase": 1,
                    "max": null,
                    "min": "0",
                    "show": true
                },
                {
                    "$$hashKey": "object:361",
                    "format": "short",
                    "label": null,
                    "logBase": 1,
                    "max": null,
                    "min": null,
                    "show": true
                }
            ],
            "yaxis": {
                "align": false,
                "alignLevel": null
            }
        },
        {
            "aliasColors": {},
            "bars": false,
            "dashLength": 10,
            "dashes": false,
            "datasource": "carbon-short",
            "decimals": 1,
            "fill": 0,
            "fillGradient": 0,
            "gridPos": {
                "h": 6,
                "w": 12,
                "x": 12,
                "y": 25
            },
            "hiddenSeries": false,
            "id": 25,
            "legend": {
                "alignAsTable": true,
                "avg": true,
                "current": false,
                "hideEmpty": true,
                "hideZero": true,
                "max": true,
                "min": false,
                "rightSide": true,
                "show": true,
                "sideWidth": 350,
                "total": false,
                "values": true
            },
            "lines": true,
            "linewidth": 1,
            "nullPointMode": "null",
            "options": {
                "alertThreshold": true
            },
            "percentage": false,
            "pluginVersion": "8.2.3",
            "pointradius": 2,
            "points": false,
            "renderer": "flot",
            "seriesOverrides": [
                {
                    "$$hashKey": "object:379",
                    "alias": "/n_cpus/",
                    "color": "#C4162A"
                },
                {
                    "$$hashKey": "object:503",
                    "alias": "/load1/",
                    "color": "#E0B400"
                },
                {
                    "$$hashKey": "object:511",
                    "alias": "/load5/",
                    "color": "#FA6400"
                },
                {
                    "$$hashKey": "object:519",
                    "alias": "/load15/",
                    "color": "#C4162A"
                }
            ],
            "spaceLength": 10,
            "stack": false,
            "steppedLine": false,
            "targets": [
                {
                    "refCount": 0,
                    "refId": "A",
                    "target": "aliasByNode(aliasByNode(seriesByTag('name=system.system.load1', 'host=~${host:regex}'), 'host', 'name'), 0, 6)",
                    "textEditor": false
                },
                {
                    "hide": false,
                    "refCount": 0,
                    "refId": "B",
                    "target": "aliasByNode(aliasByNode(seriesByTag('name=system.system.load5', 'host=~${host:regex}'), 'host', 'name'), 0, 6)",
                    "textEditor": false
                },
                {
                    "hide": false,
                    "refCount": 0,
                    "refId": "C",
                    "target": "aliasByNode(aliasByNode(seriesByTag('name=system.system.load15', 'host=~${host:regex}'), 'host', 'name'), 0, 6)",
                    "textEditor": false
                },
                {
                    "hide": false,
                    "refCount": 0,
                    "refId": "D",
                    "target": "aliasByNode(aliasByNode(seriesByTag('name=system.system.n_cpus', 'host=~${host:regex}'), 'host', 'name'), 0, 6)",
                    "textEditor": false
                }
            ],
            "thresholds": [],
            "timeFrom": null,
            "timeRegions": [],
            "timeShift": null,
            "title": "LA1",
            "tooltip": {
                "shared": true,
                "sort": 0,
                "value_type": "individual"
            },
            "type": "graph",
            "xaxis": {
                "buckets": null,
                "mode": "time",
                "name": null,
                "show": true,
                "values": []
            },
            "yaxes": [
                {
                    "$$hashKey": "object:708",
                    "decimals": 1,
                    "format": "none",
                    "label": null,
                    "logBase": 1,
                    "max": null,
                    "min": "0",
                    "show": true
                },
                {
                    "$$hashKey": "object:709",
                    "format": "short",
                    "label": null,
                    "logBase": 1,
                    "max": null,
                    "min": null,
                    "show": false
                }
            ],
            "yaxis": {
                "align": false,
                "alignLevel": null
            }
        }
    ],
    "refresh": "",
    "schemaVersion": 31,
    "style": "dark",
    "tags": [
        "hlha",
        "memcached"
    ],
    "templating": {
        "list": [
            {
                "description": null,
                "error": null,
                "hide": 2,
                "label": null,
                "name": "servertype",
                "query": "memcached",
                "skipUrlSync": false,
                "type": "constant"
            },
            {
                "allValue": null,
                "current": {
                    "selected": true,
                    "text": "prod",
                    "value": "prod"
                },
                "description": null,
                "error": null,
                "hide": 0,
                "includeAll": false,
                "label": null,
                "multi": false,
                "name": "contur",
                "options": [
                    {
                        "selected": true,
                        "text": "prod",
                        "value": "prod"
                    }
                ],
                "query": "prod",
                "queryValue": "",
                "skipUrlSync": false,
                "type": "custom"
            },
            {
                "allValue": null,
                "current": {
                    "selected": false,
                    "text": "memcached-cache.unix.tensor.ru",
                    "value": "memcached-cache.unix.tensor.ru"
                },
                "datasource": "Tagged",
                "definition": "tag_values(host,contur=$contur,servertype=$servertype)",
                "description": null,
                "error": null,
                "hide": 0,
                "includeAll": false,
                "label": "\u0425\u043e\u0441\u0442",
                "multi": false,
                "name": "host",
                "options": [],
                "query": "tag_values(host,contur=$contur,servertype=$servertype)",
                "refresh": 1,
                "regex": "",
                "skipUrlSync": false,
                "sort": 1,
                "tagValuesQuery": "",
                "tagsQuery": "",
                "type": "query",
                "useTags": false
            }
        ]
    },
    "time": {
        "from": "now-30m",
        "to": "now"
    },
    "timepicker": {},
    "timezone": "",
    "title": "HL/HA \u2014 MEMCACHED",
    "uid": "xmLWPGcnz",
    "version": 28
}